pyscrambler/__init__.py
pyscrambler/binary.py
pyscrambler/permutation.py
pyscrambler/rearrange.py
pyscrambler/scramblers/__init__.py
pyscrambler/scramblers/basescrambler.py
pyscrambler/scramblers/multiscrambler.py
pyscrambler-0.0.12.dist-info/DESCRIPTION.rst
pyscrambler-0.0.12.dist-info/METADATA
pyscrambler-0.0.12.dist-info/RECORD
pyscrambler-0.0.12.dist-info/WHEEL
pyscrambler-0.0.12.dist-info/metadata.json
pyscrambler-0.0.12.dist-info/top_level.txt
