Metadata-Version: 2.0
Name: pyscrambler
Version: 0.0.12
Summary: Concept data scrambler using permutations as a basis
Home-page: https://github.com/saxbophone/pyscrambler
Author: Joshua Saxby
Author-email: joshua.a.saxby@gmail.com
License: MIT
Platform: UNKNOWN
Classifier: Development Status :: 3 - Alpha
Classifier: Intended Audience :: Developers
Classifier: Intended Audience :: Education
Classifier: License :: OSI Approved :: MIT License
Classifier: Programming Language :: Python :: 2
Classifier: Programming Language :: Python :: 2.7
Classifier: Programming Language :: Python :: 3
Classifier: Programming Language :: Python :: 3.2
Classifier: Programming Language :: Python :: 3.3
Classifier: Programming Language :: Python :: 3.4
Classifier: Topic :: Security :: Cryptography
Requires-Dist: bitstring (==3.1.3)
Requires-Dist: oset (==0.1.3)
Provides-Extra: test
Requires-Dist: coverage (==3.7.1); extra == 'test'
